uoft_nautobot/__init__.py
uoft_nautobot/datasources.py
uoft_nautobot/jinja_filters.py
uoft_nautobot/jobs.py
uoft_nautobot/librenms.py
uoft_nautobot/api/__init__.py
uoft_nautobot/api/urls.py
uoft_nautobot/api/views.py
uoft_nautobot/diffsync/__init__.py
uoft_nautobot/diffsync/bluecat/__init__.py
uoft_nautobot/diffsync/bluecat/adapters.py
uoft_nautobot/diffsync/bluecat/models.py
uoft_nautobot/diffsync/yaml/__init__.py
uoft_nautobot/diffsync/yaml/adapters.py
uoft_nautobot/diffsync/yaml/models.py
uoft_nautobot/diffsync/yaml/test.yaml
uoft_nautobot/management/__init__.py
uoft_nautobot/management/commands/__init__.py
uoft_nautobot/management/commands/update_device_types.py
uoft_nautobot/management/commands/utsc_debug.py
uoft_nautobot-1.0.0.dist-info/METADATA
uoft_nautobot-1.0.0.dist-info/WHEEL
uoft_nautobot-1.0.0.dist-info/RECORD
