Metadata-Version: 2.1
Name: uoft_nautobot
Version: 1.0.0
Summary: A collection of UofT-specific modifications and extensions to Nautobot.
Author-email: Alex Tremblay <alex.tremblay@utoronto.ca>, University of Toronto Governing Council <governing.council@utoronto.ca>
Requires-Python: >=3.10
Requires-Dist: debugpy
Requires-Dist: django-auth-ldap
Requires-Dist: django-debug-toolbar
Requires-Dist: django-environ
Requires-Dist: html-table-parser-python3>=0.2.0
Requires-Dist: librenms-handler
Requires-Dist: napalm
Requires-Dist: nautobot-golden-config
Requires-Dist: nautobot-ssot>=1.1.0
Requires-Dist: nautobot>=1.3
Requires-Dist: python-box
Requires-Dist: uoft-core
